{"name":"Cv","tagline":"resume","body":"# Eoin Smith\r\n\r\n## Details\r\n\r\n- eoinsmith001@gmail.com\r\n- https://ie.linkedin.com/in/eoinsmith001\r\n\r\n## Technical Overview\r\n\r\n- DevOps\r\n\t- TDD: Unit, Integration, Acceptance, Performance, End-to-End testing\r\n\t- Automation: build, deploy, test, orchestration, dashboarding\r\n\t- Continuous Integration/Continuous Delivery with Go, Jenkins, git, svn, etc.\r\n\r\n- Languages/Tools\r\n\t- Languages: Python, C#, C++, Javascript, C\r\n\t- Frameworks: NodeJS, .NET\r\n\t- Infrastructure as Code: Ansible, AWS, Vagrant, Docker\r\n\t- Unix tools: bash, vi, gnuplot, all standard utilities\r\n\t- RESTful services, Web Services\r\n\r\n## Work Practices Overview\r\n\r\n- Agile/Scrum Project Delivery\r\n\t- Iterations, Planning/Requirements, Estimation, Backlog, Stories/Features/Epics, Pair Programming, Ceremonies\r\n- Ops/Reactive\r\n\t- Experience with post-delivery support, manual investigation and maintenance\r\n\r\n## Professional Experience\r\n\r\n- 2013-2015: Consultant Developer, [ThoughtWorks](http://www.thoughtworks.com), Brisbane, Australia\r\n\t- ThoughtWorks is a global professional services company providing software development and consulting for corporate clients, covering design, development, operations, project management, and transformation projects.  There is a strong emphasis on embedded development resources/Agile teams driving innovation using fast-feedback enabled by test-driven development, aggressive automation, and paired-programming.\r\n\t- Engagement 1: Developer; Online-Ordering application (Web/iOS/Android) for a national Pizza retailer\r\n\t\t- embedded on-site with client in an Agile team (~12 people) as a Developer\r\n\t\t- Delivery of features on a 2-week Agile iteration schedule\r\n\t\t- Issue Management with Trello\r\n\t\t- .NET/SQLServer/HTML5/Javascript development for Web Application managing iOS and Android applications\r\n\t\t- Combination of RESTful and Web Services\r\n\t\t- CI/CD implemented using Go, git-tfs, TDD (NUnit, jasmine, Cucumber, Selenium WebDriver), paired programming\r\n\t- Engagement 2: Developer/Operations; Migration of platform & applications to Cloud for a national insurance/banking company\r\n\t\t- embedded on-site with client in an Agile team (~10 people) as a Developer/DevOps\r\n\t\t- Issue Management with Jira/Confluence\r\n\t\t- Ansible/AWS/Java/bash/Python development of Cloud Infrastructure for insurance claim processing web application\r\n\t\t- CI/CD implemented using Jenkins, git & svn, TDD (bash, PyUnit, curl), paired programming\r\n\t\t- Project management experience: scoping, estimating, planning, tracking, leading of cermonies (retrospective, showcase, etc.)\r\n\t\t- Assistance with HR process for client; code reviews, interviews\r\n\t- Additional ThoughtWorks duties\r\n\t\t- HR process; code review, paired coding exercises, interviews\r\n\t\t- Compiled and delivered a presentation on Continuous Delivery to University of Queensland computing students\r\n\r\n- 2010-2013: Performance Tester/System Engineer/Product Support, [Murex](https://www.murex.com), Dublin, Ireland\r\n\t- A global company developing and supporting a financial processing platform implementing trading, risk management and processing solutions.  The Dublin office develops the real-time risk exposure calculation module provided to over 100 clients.\r\n\t- Team of 3, working complementing development team of ~20\r\n\t- Performance Tester\r\n\t\t- Development of automation framework for performance testing, using Python/bash\r\n\t\t- Profiling, analysis, and investigation using jstack, jmap, jprofiler and similar tools\r\n\t\t- automation of test cases/schedules\r\n\t- System Engineer\r\n\t\t- Maintenance of test environments for multiple client mirrors using scripting/bash\r\n\t\t- Documentation using Confluence\r\n\t- Product Support\r\n\t\t- Reproduction and debugging of client issues (environment copies, investigation, test automation)\r\n\t\t- Release support (documentation, configuration testing & recommendations)\r\n\t\t- Pre-release UAT (manual testing)\r\n\t\t- Documentation of technical features and functionality\r\n\t\t- Compiled and delivered a 3-day training course covering technical, practical and case-study material to companion office off-site in Beirut, Lebanon\r\n- 2008-2010: Developer (Research Fellow), LHCb experiment, [CERN](http://home.web.cern.ch), Geneva, Switzerland\r\n\t- CERN is the European particle physics research laboratory providing particle accelerators and infrastructure for high-energy physics research.  The LHCb software group provide applications and computing resources for the LHCb physics group.\r\n\t- Project: Parallelisation of legacy simulation & analysis applications\r\n\t\t- Python/C++ development: Python modules to integrate with C++ legacy code, splitting and aggregating high-volume jobs\r\n\t\t- Prepared a publication for CHEP 2009 (International Conference on Computing in High Energy and Nuclear Physics)\r\n- 2007-2008: Intern, [NTNU Technology Transfer](http://www.ntnu.no), Trondheim, Norway\r\n\t- Tech transfer company working on commercialisation of research projects from the Norwegian University of Science and Technology\r\n\t\t- Internship, Business Development\r\n\r\n## Education\r\n\r\n- BSc Hons Mathematical Science, UCD\r\n\t- Graduated 2006\r\n\t- Modules taken from Pure Maths, Applied Maths, Statistics\r\n\t- Computational Mathematics including development in Java, C, Matlab, Sass\r\n\r\n\r\n- Leaving Certificate, Ard Scoil Chiarain Naofa, Clara, Offaly, Ireland\r\n\t- 555 points\r\n\t- A1 English, French, Physics&Chemistry\r\n\r\n## Hobbies/Interests\r\n- Cooking\r\n- Guitar & Turntables\r\n- Running\r\n","google":"","note":"Don't delete this file! It's used internally to help with page regeneration."}